fastflix/__init__.py
fastflix/__main__.py
fastflix/application.py
fastflix/audio_processing.py
fastflix/command_runner.py
fastflix/conversion_worker.py
fastflix/entry.py
fastflix/exceptions.py
fastflix/ff_queue.py
fastflix/flix.py
fastflix/gpu_detect.py
fastflix/language.py
fastflix/program_downloads.py
fastflix/resources.py
fastflix/rigaya_helpers.py
fastflix/shared.py
fastflix/version.py
fastflix/windows_tools.py
fastflix/data/Info.plist.template
fastflix/data/icon.icns
fastflix/data/icon.ico
fastflix/data/languages.yaml
fastflix/data/encoders/icon_av1_aom.png
fastflix/data/encoders/icon_gif.png
fastflix/data/encoders/icon_h264_toolbox.png
fastflix/data/encoders/icon_hevc_toolbox.png
fastflix/data/encoders/icon_nvenc.png
fastflix/data/encoders/icon_nvencc.png
fastflix/data/encoders/icon_qsvencc.png
fastflix/data/encoders/icon_rav1e.png
fastflix/data/encoders/icon_svt_av1.png
fastflix/data/encoders/icon_vaapi.png
fastflix/data/encoders/icon_vceencc.png
fastflix/data/encoders/icon_vp9.png
fastflix/data/encoders/icon_vvc.png
fastflix/data/encoders/icon_webp.png
fastflix/data/encoders/icon_x264.png
fastflix/data/encoders/icon_x265.png
fastflix/data/icons/loading.gif
fastflix/data/icons/onyx-add-queue.svg
fastflix/data/icons/onyx-convert.svg
fastflix/data/icons/black/black-x.svg
fastflix/data/icons/black/down-arrow.svg
fastflix/data/icons/black/edit-box.svg
fastflix/data/icons/black/info.svg
fastflix/data/icons/black/onyx-advanced.svg
fastflix/data/icons/black/onyx-audio.svg
fastflix/data/icons/black/onyx-cc.svg
fastflix/data/icons/black/onyx-clear-queue.svg
fastflix/data/icons/black/onyx-copy.svg
fastflix/data/icons/black/onyx-cover.svg
fastflix/data/icons/black/onyx-file-search.svg
fastflix/data/icons/black/onyx-magnifier.svg
fastflix/data/icons/black/onyx-new-profile.svg
fastflix/data/icons/black/onyx-output.svg
fastflix/data/icons/black/onyx-pause.svg
fastflix/data/icons/black/onyx-quality.svg
fastflix/data/icons/black/onyx-queue.svg
fastflix-5.12.0.dist-info/licenses/AUTHORS
fastflix-5.12.0.dist-info/licenses/LICENSE
fastflix-5.12.0.dist-info/METADATA
fastflix-5.12.0.dist-info/WHEEL
fastflix-5.12.0.dist-info/entry_points.txt
fastflix-5.12.0.dist-info/top_level.txt
fastflix-5.12.0.dist-info/RECORD
