Metadata-Version: 2.4
Name: fastflix
Version: 5.12.0
Summary: GUI Encoder
Author-email: Chris Griffith <chris@cdgriffith.com>
Requires-Python: >=3.12
License-File: LICENSE
License-File: AUTHORS
Requires-Dist: platformdirs~=4.3
Requires-Dist: chardet<5.2.0,>=5.1.0
Requires-Dist: colorama<1.0,>=0.4
Requires-Dist: coloredlogs<16.0,>=15.0
Requires-Dist: iso639-lang==0.0.9
Requires-Dist: mistune<3.0,>=2.0
Requires-Dist: packaging>=23.2
Requires-Dist: pathvalidate<3.0,>=2.4
Requires-Dist: psutil<6.0,>=5.9
Requires-Dist: pydantic<3.0,>=2.0
Requires-Dist: pyside6==6.9.0
Requires-Dist: python-box[all]<7.0,>=6.0
Requires-Dist: requests<3.0,>=2.28
Requires-Dist: reusables<0.10.0,>=0.9.6
Requires-Dist: setuptools>=75.8
Requires-Dist: wmi>=1.5.1; sys_platform == "win32"
Requires-Dist: ffmpeg-normalize<2.0,>=1.31.3
Provides-Extra: develop
Requires-Dist: wheel>=0.38.4; extra == "develop"
Requires-Dist: typing_extensions>=4.4; extra == "develop"
Requires-Dist: pyinstaller==6.9.0; extra == "develop"
Requires-Dist: pytest>=7.3; extra == "develop"
Requires-Dist: types-requests>=2.28; extra == "develop"
Requires-Dist: types-setuptools>=65.7; extra == "develop"
Requires-Dist: pre-commit>=3.0.3; extra == "develop"
Dynamic: license-file
